lib/__init__.py
lib/cli.py
lib/commands/README.md
lib/commands/__init__.py
lib/commands/delete_user_media.py
lib/commands/discovery.py
lib/commands/es_index_zbxhost.py
lib/commands/fs_calc.py
lib/commands/gen_analaysis_report.py
lib/commands/hostgrp_aggr_item.py
lib/commands/hosttpl.py
lib/commands/inventory_supplementary.py
lib/commands/ldap_usergrp.py
lib/commands/multi_interfaces.py
lib/commands/oob.py
lib/commands/send_to_all_users.py
lib/commands/service_tree.py
lib/commands/sync_wework_media.py
lib/commands/update_hostgrp_poc.py
lib/commands/update_hostname.py
lib/commands/vmware_host_inventory.py
lib/utils/README.md
lib/utils/__init__.py
lib/utils/configs.ini
lib/utils/docs.py
lib/utils/esapis.py
lib/utils/esxiapis.py
lib/utils/format.py
lib/utils/ldapapis.py
lib/utils/wxapis.py
lib/utils/zbxapis.py
lib/utils/zbxtags.py
zbxtool_cfomp-0.11.18.dist-info/LICENSE
zbxtool_cfomp-0.11.18.dist-info/METADATA
zbxtool_cfomp-0.11.18.dist-info/WHEEL
zbxtool_cfomp-0.11.18.dist-info/entry_points.txt
zbxtool_cfomp-0.11.18.dist-info/top_level.txt
zbxtool_cfomp-0.11.18.dist-info/zip-safe
zbxtool_cfomp-0.11.18.dist-info/RECORD
