Metadata-Version: 2.1
Name: zbxtool-cfomp
Version: 0.11.18
Summary: A Zabbix Manager Tool
Home-page: UNKNOWN
Author: UNKNOWN
Author-email: UNKNOWN
License: UNKNOWN
Platform: Linux
Platform: Windows
Requires-Dist: IPy >=1.01
Requires-Dist: convertapi ==1.5.0
Requires-Dist: diskcache >=5.4.0
Requires-Dist: elasticsearch ==7.17.0
Requires-Dist: infi.pyutils >=1.1.3
Requires-Dist: infi.pyvmomi-wrapper >=0.1.29
Requires-Dist: infi >=0.0.1
Requires-Dist: jmespath >=0.10.0
Requires-Dist: ldap3 >=2.9.1
Requires-Dist: multicommand ==0.1.1
Requires-Dist: numpy ==1.19.5
Requires-Dist: openpyxl ==3.0.9
Requires-Dist: packaging >=21.0
Requires-Dist: pandas ==1.1.5
Requires-Dist: prettytable ==2.0.0
Requires-Dist: pyVmomi ==7.0.3
Requires-Dist: python-dateutil >=2.8.2
Requires-Dist: python-docx ==0.8.11
Requires-Dist: weworkapi-cfomp >=1.1.4
Requires-Dist: zabbix-api >=0.5.4
